{
  "project_info": {
    "project_number": "724255769414",
    "firebase_url": "https://flaya-40942-default-rtdb.firebaseio.com",
    "project_id": "flaya-40942",
    "storage_bucket": "flaya-40942.firebasestorage.app"
  },
  "client": [
    {
      "client_info": {
        "mobilesdk_app_id": "1:724255769414:android:d0471aa449706539245b47",
        "android_client_info": {
          "package_name": "com.company.stryt"
        }
      },
      "oauth_client": [
        {
          "client_id": "724255769414-gp00pm4vcc58opm8dptgr8t3odfi5gvh.apps.googleusercontent.com",
          "client_type": 1,
          "android_info": {
            "package_name": "com.company.stryt",
            "certificate_hash": "f5a2b176b8de6b99e9ef6dc62c36539b0362c2ea"
          }
        },
        {
          "client_id": "724255769414-kld4c00dpkt417r4ujujeuku9gs0b0dl.apps.googleusercontent.com",
          "client_type": 1,
          "android_info": {
            "package_name": "com.company.stryt",
            "certificate_hash": "7f8ac22bf8892653743e4fce528bc95906c81157"
          }
        },
        {
          "client_id": "724255769414-pbq26jaadrvp5jcks4lfihrkfe8k9rm6.apps.googleusercontent.com",
          "client_type": 3
        }
      ],
      "api_key": [
        {
          "current_key": "AIzaSyDReLXW-WnLovw2UyqqB69efB7apgWkKrQ"
        }
      ],
      "services": {
        "appinvite_service": {
          "other_platform_oauth_client": [
            {
              "client_id": "724255769414-pbq26jaadrvp5jcks4lfihrkfe8k9rm6.apps.googleusercontent.com",
              "client_type": 3
            }
          ]
        }
      }
    },
    {
      "client_info": {
        "mobilesdk_app_id": "1:724255769414:android:7354cc5009148b92245b47",
        "android_client_info": {
          "package_name": "com.flayasapp.flayaco"
        }
      },
      "oauth_client": [
        {
          "client_id": "724255769414-6tgcloqdt969fnfgsa40e2qkmqf3e1nj.apps.googleusercontent.com",
          "client_type": 1,
          "android_info": {
            "package_name": "com.flayasapp.flayaco",
            "certificate_hash": "b38b4ecc3fc11f008069e3e8e25e7c1c180906e7"
          }
        },
        {
          "client_id": "724255769414-7rk83id6pquf3eio431hia4hi2em6k9s.apps.googleusercontent.com",
          "client_type": 1,
          "android_info": {
            "package_name": "com.flayasapp.flayaco",
            "certificate_hash": "b243803d32159128b40a409a094b157b0bce6fe7"
          }
        },
        {
          "client_id": "724255769414-ms6ncqvdc78a6tamktajrq88rj3eero4.apps.googleusercontent.com",
          "client_type": 1,
          "android_info": {
            "package_name": "com.flayasapp.flayaco",
            "certificate_hash": "8a3a31f984206a93fde588f320913fd8d9b5a430"
          }
        },
        {
          "client_id": "724255769414-ve3ism0773m2cetld50octgsa97cvpld.apps.googleusercontent.com",
          "client_type": 1,
          "android_info": {
            "package_name": "com.flayasapp.flayaco",
            "certificate_hash": "9249cab6babc02854342dcc850b86c925382e10f"
          }
        },
        {
          "client_id": "724255769414-pbq26jaadrvp5jcks4lfihrkfe8k9rm6.apps.googleusercontent.com",
          "client_type": 3
        }
      ],
      "api_key": [
        {
          "current_key": "AIzaSyDReLXW-WnLovw2UyqqB69efB7apgWkKrQ"
        }
      ],
      "services": {
        "appinvite_service": {
          "other_platform_oauth_client": [
            {
              "client_id": "724255769414-pbq26jaadrvp5jcks4lfihrkfe8k9rm6.apps.googleusercontent.com",
              "client_type": 3
            }
          ]
        }
      }
    }
  ],
  "configuration_version": "1"
}